LTTL/Input.py
LTTL/Processor.py
LTTL/ProcessorThread.py
LTTL/Segment.py
LTTL/Segmentation.py
LTTL/Segmenter.py
LTTL/SegmenterThread.py
LTTL/Table.py
LTTL/TableThread.py
LTTL/Utils.py
LTTL/__init__.py
LTTL-2.1.0.dist-info/LICENSE
LTTL-2.1.0.dist-info/METADATA
LTTL-2.1.0.dist-info/WHEEL
LTTL-2.1.0.dist-info/top_level.txt
LTTL-2.1.0.dist-info/RECORD
